{"cameraMode":{"drawMode":0,"name":"Shaded","section":"Shading Mode"},"sceneLighting":false,"audioPlay":false,"sceneViewState":{"m_AlwaysRefresh":false,"showFog":false,"showSkybox":false,"showFlares":false,"showImageEffects":false,"showParticleSystems":false,"showVisualEffectGraphs":true,"m_FxEnabled":true},"in2DMode":false,"pivot":{"x":-0.9982673525810242,"y":0.8417253494262695,"z":0.639867901802063},"rotation":{"x":0.15117041766643525,"y":0.1955288052558899,"z":-0.030439725145697595,"w":0.9685788750648499},"size":3.515183210372925,"orthographic":true}