{"cameraMode":{"drawMode":0,"name":"Shaded","section":"Shading Mode"},"sceneLighting":true,"audioPlay":false,"sceneViewState":{"m_AlwaysRefresh":false,"showFog":true,"showSkybox":true,"showFlares":true,"showImageEffects":true,"showParticleSystems":true,"showVisualEffectGraphs":true,"m_FxEnabled":false},"in2DMode":false,"pivot":{"x":653.023681640625,"y":219.79718017578126,"z":221.18264770507813},"rotation":{"x":0.45253312587738039,"y":0.19097892940044404,"z":-0.0998254343867302,"w":0.8653886914253235},"size":780.8543090820313,"orthographic":false}